coa_dev_coagent/__init__.py
coa_dev_coagent/client.py
coa_dev_coagent/logapi.py
coa_dev_coagent/py.typed
coa_dev_coagent-0.7.1.dist-info/WHEEL
coa_dev_coagent-0.7.1.dist-info/METADATA
coa_dev_coagent-0.7.1.dist-info/RECORD
