Metadata-Version: 2.3
Name: coa-dev-coagent
Version: 0.7.1
Summary: CoAgent can help you assess, test, and monitor AI models and agents
Author: Coagent Developers
Author-email: Coagent Developers <team@infinyon.com>
Requires-Dist: requests>=2.31.0
Requires-Dist: pytest>=7.4.0 ; extra == 'test'
Requires-Dist: pytest-mock>=3.11.1 ; extra == 'test'
Requires-Dist: responses>=0.23.0 ; extra == 'test'
Requires-Python: >=3.10
Provides-Extra: test
